datar_pandas/__init__.py
datar_pandas/api/__init__.py
datar_pandas/api/base/__init__.py
datar_pandas/api/base/arithm.py
datar_pandas/api/base/asis.py
datar_pandas/api/base/bessel.py
datar_pandas/api/base/complex.py
datar_pandas/api/base/cum.py
datar_pandas/api/base/factor.py
datar_pandas/api/base/funs.py
datar_pandas/api/base/null.py
datar_pandas/api/base/random.py
datar_pandas/api/base/seq.py
datar_pandas/api/base/special.py
datar_pandas/api/base/string.py
datar_pandas/api/base/table.py
datar_pandas/api/base/trig.py
datar_pandas/api/base/verbs.py
datar_pandas/api/base/which.py
datar_pandas/api/dplyr/__init__.py
datar_pandas/api/dplyr/_rank.py
datar_pandas/api/dplyr/across.py
datar_pandas/api/dplyr/arrange.py
datar_pandas/api/dplyr/bind.py
datar_pandas/api/dplyr/context.py
datar_pandas/api/dplyr/count_tally.py
datar_pandas/api/dplyr/desc.py
datar_pandas/api/dplyr/distinct.py
datar_pandas/api/dplyr/filter_.py
datar_pandas/api/dplyr/funs.py
datar_pandas/api/dplyr/glimpse.py
datar_pandas/api/dplyr/group_by.py
datar_pandas/api/dplyr/group_data.py
datar_pandas/api/dplyr/group_iter.py
datar_pandas/api/dplyr/if_else.py
datar_pandas/api/dplyr/join.py
datar_pandas/api/dplyr/lead_lag.py
datar_pandas/api/dplyr/mutate.py
datar_pandas/api/dplyr/order_by.py
datar_pandas/api/dplyr/pick.py
datar_pandas/api/dplyr/pull.py
datar_pandas/api/dplyr/rank.py
datar_pandas/api/dplyr/recode.py
datar_pandas/api/dplyr/reframe.py
datar_pandas/api/dplyr/relocate.py
datar_pandas/api/dplyr/rename.py
datar_pandas/api/dplyr/rows.py
datar_pandas/api/dplyr/select.py
datar_pandas/api/dplyr/sets.py
datar_pandas/api/dplyr/slice_.py
datar_pandas/api/dplyr/summarise.py
datar_pandas/api/dplyr/tidyselect.py
datar_pandas/api/forcats/__init__.py
datar_pandas/api/forcats/fct_multi.py
datar_pandas/api/forcats/lvl_addrm.py
datar_pandas/api/forcats/lvl_order.py
datar_pandas/api/forcats/lvl_value.py
datar_pandas/api/forcats/lvls.py
datar_pandas/api/forcats/misc.py
datar_pandas/api/forcats/utils.py
datar_pandas-0.5.7.dist-info/METADATA
datar_pandas-0.5.7.dist-info/WHEEL
datar_pandas-0.5.7.dist-info/entry_points.txt
datar_pandas-0.5.7.dist-info/RECORD
